polycube/__init__.py
polycube/polycube.py
polycube/stl.py
polycube-0.0.1.dist-info/LICENSE
polycube-0.0.1.dist-info/METADATA
polycube-0.0.1.dist-info/WHEEL
polycube-0.0.1.dist-info/top_level.txt
polycube-0.0.1.dist-info/RECORD
