Metadata-Version: 2.1
Name: polycube
Version: 0.0.1
Summary: A package for constructing polycube models
Home-page: https://github.com/donsheehy/polycube
Author: Donald R. Sheehy
Author-email: don.r.sheehy@gmail.com
Classifier: Programming Language :: Python :: 3
Classifier: License :: OSI Approved :: MIT License
Classifier: Operating System :: OS Independent
Requires-Python: >=3.6
License-File: LICENSE
Requires-Dist: solidpython
